TriModelSystem/__init__.py
TriModelSystem/binclassification.py
TriModelSystem/tms_utils.py
TriModelSystem/utils.py
TriModelSystem-0.0.3.dist-info/METADATA
TriModelSystem-0.0.3.dist-info/WHEEL
TriModelSystem-0.0.3.dist-info/top_level.txt
TriModelSystem-0.0.3.dist-info/RECORD
