Metadata-Version: 2.1
Name: TriModelSystem
Version: 0.0.3
Summary: Tri-Model Ensemble System for Classification
Author: Arkitech (Joshua Tan)
Author-email: <joshuatan.helios@gmail.com>
Keywords: python,machine learning,tensorflow,classification,neural network
Classifier: Development Status :: 2 - Pre-Alpha
Classifier: Intended Audience :: Science/Research
Classifier: Programming Language :: Python :: 3
Classifier: Operating System :: Unix
Classifier: Operating System :: MacOS :: MacOS X
Classifier: Operating System :: Microsoft :: Windows
Requires-Dist: tensorflow
